{
  "schemaVersion": "prometheus-skill-bundle-v1",
  "entrypoint": "SKILL.md",
  "triggers": [
    "hyperframes",
    "HyperFrames video",
    "promo video",
    "launch video",
    "voice mode video",
    "avoid AI tells",
    "purple blue gradient",
    "rounded panels",
    "AI-looking video",
    "generator-looking video"
  ],
  "categories": [
    "creative",
    "video",
    "hyperframes",
    "motion-design"
  ],
  "requiredTools": [
    "workspace_write",
    "media_quality"
  ],
  "id": "hyperframes"
}
