{
  "schemaVersion": "prometheus-skill-bundle-v1",
  "id": "git-workflow",
  "name": "git-workflow",
  "description": "Don't guess git commands. Use this reference for all git and GitHub CLI operations.",
  "version": "1.0.0",
  "entrypoint": "SKILL.md",
  "triggers": [],
  "categories": [],
  "requiredTools": [],
  "permissions": {},
  "resources": [
    {
      "path": "notes/github-cli-full-access-setup-2026-05-16.md",
      "type": "doc",
      "description": "Guardrail for safely setting up full local GitHub CLI access without leaking tokens."
    }
  ]
}
